go_data_creator_for_algotrade/__init__.py
go_data_creator_for_algotrade/data_creator.py
go_data_creator_for_algotrade-0.1.dist-info/METADATA
go_data_creator_for_algotrade-0.1.dist-info/WHEEL
go_data_creator_for_algotrade-0.1.dist-info/top_level.txt
go_data_creator_for_algotrade-0.1.dist-info/RECORD
