Metadata-Version: 2.1
Name: go-data-creator-for-algotrade
Version: 0.1
Summary: A data creation and formatting tool for algo trading
Home-page: UNKNOWN
Author: okan.uregen
License: UNKNOWN
Platform: UNKNOWN
Classifier: Programming Language :: Python :: 3
Requires-Dist: pymssql
Requires-Dist: pandas
